{
  "appKey": "",
  "appSecret": "",
  "encryptJs": true,
  "excludeScenes": [],
  "fb-instant-games": {},
  "includeAnySDK": false,
  "includeSDKBox": false,
  "inlineSpriteFrames": true,
  "inlineSpriteFrames_native": true,
  "jailbreakPlatform": false,
  "md5Cache": true,
  "mergeStartScene": false,
  "oauthLoginServer": "",
  "optimizeHotUpdate": false,
  "orientation": {
    "landscapeLeft": true,
    "landscapeRight": true,
    "portrait": false,
    "upsideDown": false
  },
  "packageName": "org.cocos2d.helloworld",
  "privateKey": "",
  "qqplay": {
    "REMOTE_SERVER_ROOT": "",
    "orientation": "portrait"
  },
  "renderMode": "0",
  "startScene": "8c50572f-3f0c-4a5e-a022-ba0d0458c088",
  "title": "RunGame",
  "webOrientation": "landscape",
  "wechatgame": {
    "REMOTE_SERVER_ROOT": "",
    "appid": "wx75e98920c899fe29",
    "isSubdomain": false,
    "orientation": "landscape",
    "subContext": ""
  },
  "xxteaKey": "bd7494c1-fecd-4e",
  "zipCompressJs": true
}